<?xml version='1.0'?>
<properties>
      <property>
            <name>name</name>
            <type>text</type>
            <table>objects</table>
            <field>name</field>
            <caption>Aadress</caption>
      </property>
      <property>
            <name>administrative_structure</name>
            <table>aw_address</table>
            <group>general</group>
            <type>hidden</type>
            <field>administrative_structure</field>
      </property>
      <property>
            <name>country</name>
            <table>aw_address</table>
            <group>general</group>
            <type>select</type>
            <field>country</field>
            <caption>Riik</caption>
      </property>
      <property>
            <name>location_data</name>
            <table>aw_address</table>
            <group>general</group>
            <type>hidden</type>
            <store>no</store>
            <field>location_data</field>
      </property>
      <property>
            <name>location</name>
            <table>aw_address</table>
            <group>general</group>
            <type>textbox</type>
            <store>no</store>
            <field>location</field>
            <caption>Asukoht</caption>
      </property>
      <property>
            <name>street</name>
            <table>aw_address</table>
            <group>general</group>
            <type>textbox</type>
            <maxlength>250</maxlength>
            <field>street</field>
            <caption>T&amp;amp;auml;nav/asum</caption>
      </property>
      <property>
            <name>house</name>
            <table>aw_address</table>
            <group>general</group>
            <type>textbox</type>
            <maxlength>250</maxlength>
            <field>house</field>
            <caption>Maja/number</caption>
      </property>
      <property>
            <name>apartment</name>
            <table>aw_address</table>
            <group>general</group>
            <type>textbox</type>
            <maxlength>50</maxlength>
            <field>apartment</field>
            <caption>Korter/Tuba</caption>
      </property>
      <property>
            <name>postal_code</name>
            <table>aw_address</table>
            <group>general</group>
            <type>textbox</type>
            <maxlength>25</maxlength>
            <field>postal_code</field>
            <caption>Postiindeks</caption>
      </property>
      <property>
            <name>po_box</name>
            <table>aw_address</table>
            <group>general</group>
            <type>textbox</type>
            <maxlength>50</maxlength>
            <field>po_box</field>
            <caption>Postkast</caption>
      </property>
      <classinfo>
            <syslog_type>ST_ADDRESS</syslog_type>
            <relationmgr>yes</relationmgr>
            <no_comment>1</no_comment>
            <no_status>1</no_status>
            <maintainer>voldemar</maintainer>
            <prop_cb>1</prop_cb>
      </classinfo>
      <tableinfo>
            <aw_address>
                  <index>aw_oid</index>
                  <master_index>brother_of</master_index>
                  <master_table>objects</master_table>
            </aw_address>
      </tableinfo>
</properties>

