<?xml version='1.0'?>
<properties>
      <property>
            <name>mgr_tb</name>
            <table>objects</table>
            <group>mgr</group>
            <field>meta</field>
            <method>serialize</method>
            <type>toolbar</type>
            <no_caption>1</no_caption>
            <store>no</store>
      </property>
      <property>
            <name>mgr_tree</name>
            <table>objects</table>
            <group>mgr</group>
            <field>meta</field>
            <method>serialize</method>
            <type>treeview</type>
            <no_caption>1</no_caption>
            <parent>mgr_tree_box</parent>
            <store>no</store>
      </property>
      <property>
            <name>mgr_tbl</name>
            <table>objects</table>
            <group>mgr</group>
            <field>meta</field>
            <method>serialize</method>
            <type>table</type>
            <no_caption>1</no_caption>
            <parent>mgr_hbox</parent>
            <store>no</store>
      </property>
      <property>
            <name>rels_tb</name>
            <table>objects</table>
            <group>rels</group>
            <field>meta</field>
            <method>serialize</method>
            <type>toolbar</type>
            <no_caption>1</no_caption>
            <store>no</store>
      </property>
      <property>
            <name>rels_tree</name>
            <table>objects</table>
            <group>rels</group>
            <field>meta</field>
            <method>serialize</method>
            <type>treeview</type>
            <no_caption>1</no_caption>
            <parent>rels_tree_box</parent>
            <store>no</store>
      </property>
      <property>
            <name>rels_tbl</name>
            <table>objects</table>
            <group>rels</group>
            <field>meta</field>
            <method>serialize</method>
            <type>table</type>
            <no_caption>1</no_caption>
            <parent>rels_hbox</parent>
            <store>no</store>
      </property>
      <property>
            <name>toolbar</name>
            <table>objects</table>
            <group>classes_classes</group>
            <field>meta</field>
            <method>serialize</method>
            <type>toolbar</type>
            <no_caption>1</no_caption>
            <store>no</store>
      </property>
      <property>
            <name>classes_tree</name>
            <table>objects</table>
            <group>classes_classes</group>
            <field>meta</field>
            <method>serialize</method>
            <type>treeview</type>
            <no_caption>1</no_caption>
            <parent>classes_tree</parent>
            <store>no</store>
      </property>
      <property>
            <name>classes_groups</name>
            <table>objects</table>
            <group>classes_classes</group>
            <field>meta</field>
            <method>serialize</method>
            <type>treeview</type>
            <no_caption>1</no_caption>
            <parent>classes_groups</parent>
            <store>no</store>
      </property>
      <property>
            <name>classes_list</name>
            <table>objects</table>
            <group>classes_classes</group>
            <field>meta</field>
            <method>serialize</method>
            <type>table</type>
            <no_caption>1</no_caption>
            <store>no</store>
            <parent>classes_split</parent>
      </property>
      <property>
            <name>props_toolbar</name>
            <table>objects</table>
            <group>classes_props</group>
            <field>meta</field>
            <method>serialize</method>
            <type>toolbar</type>
            <no_caption>1</no_caption>
            <store>no</store>
      </property>
      <property>
            <name>classes_props_tree</name>
            <table>objects</table>
            <group>classes_props</group>
            <field>meta</field>
            <method>serialize</method>
            <type>treeview</type>
            <no_caption>1</no_caption>
            <parent>classes_props_tree</parent>
            <store>no</store>
      </property>
      <property>
            <name>classes_props_groups</name>
            <table>objects</table>
            <group>classes_props</group>
            <field>meta</field>
            <method>serialize</method>
            <type>treeview</type>
            <no_caption>1</no_caption>
            <parent>classes_props_groups</parent>
            <store>no</store>
      </property>
      <property>
            <name>classes_props_list</name>
            <table>objects</table>
            <group>classes_props</group>
            <field>meta</field>
            <method>serialize</method>
            <type>table</type>
            <no_caption>1</no_caption>
            <store>no</store>
            <parent>classes_props_split</parent>
      </property>
      <property>
            <name>cl_usage_stats_tree</name>
            <table>objects</table>
            <group>cl_usage_stats_clids</group>
            <field>meta</field>
            <method>serialize</method>
            <type>treeview</type>
            <no_caption>1</no_caption>
            <parent>cl_usage_stats_tree</parent>
            <store>no</store>
      </property>
      <property>
            <name>cl_usage_stats_groups</name>
            <table>objects</table>
            <group>cl_usage_stats_clids</group>
            <field>meta</field>
            <method>serialize</method>
            <type>treeview</type>
            <no_caption>1</no_caption>
            <parent>cl_usage_stats_groups</parent>
            <store>no</store>
      </property>
      <property>
            <name>cl_usage_stats_list_gpx</name>
            <table>objects</table>
            <group>cl_usage_stats_clids</group>
            <field>meta</field>
            <method>serialize</method>
            <type>google_chart</type>
            <no_caption>1</no_caption>
            <store>no</store>
            <parent>cl_usage_stats_right_split_1_v</parent>
      </property>
      <property>
            <name>cl_usage_stats_list</name>
            <table>objects</table>
            <group>cl_usage_stats_clids</group>
            <field>meta</field>
            <method>serialize</method>
            <type>table</type>
            <no_caption>1</no_caption>
            <store>no</store>
            <parent>cl_usage_stats_right_split_1</parent>
      </property>
      <property>
            <name>site_usage_stats_list_gpx</name>
            <table>objects</table>
            <group>cl_usage_stats_clids</group>
            <field>meta</field>
            <method>serialize</method>
            <type>google_chart</type>
            <no_caption>1</no_caption>
            <store>no</store>
            <parent>cl_usage_stats_right_split_2_v</parent>
      </property>
      <property>
            <name>site_usage_stats_list</name>
            <table>objects</table>
            <group>cl_usage_stats_clids</group>
            <field>meta</field>
            <method>serialize</method>
            <type>table</type>
            <no_caption>1</no_caption>
            <store>no</store>
            <parent>cl_usage_stats_right_split_2</parent>
      </property>
      <property>
            <name>cl_usage_props_stats_tree</name>
            <table>objects</table>
            <group>cl_usage_stats_props</group>
            <field>meta</field>
            <method>serialize</method>
            <type>treeview</type>
            <no_caption>1</no_caption>
            <parent>cl_usage_props_stats_tree</parent>
            <store>no</store>
      </property>
      <property>
            <name>cl_usage_props_stats_groups</name>
            <table>objects</table>
            <group>cl_usage_stats_props</group>
            <field>meta</field>
            <method>serialize</method>
            <type>treeview</type>
            <no_caption>1</no_caption>
            <parent>cl_usage_props_stats_groups</parent>
            <store>no</store>
      </property>
      <property>
            <name>cl_usage_props_stats_list_gpx</name>
            <table>objects</table>
            <group>cl_usage_stats_props</group>
            <field>meta</field>
            <method>serialize</method>
            <type>google_chart</type>
            <no_caption>1</no_caption>
            <store>no</store>
            <parent>cl_usage_props_stats_right_split_v</parent>
      </property>
      <property>
            <name>cl_usage_props_stats_list</name>
            <table>objects</table>
            <group>cl_usage_stats_props</group>
            <field>meta</field>
            <method>serialize</method>
            <type>table</type>
            <no_caption>1</no_caption>
            <store>no</store>
            <parent>cl_usage_props_stats_right_split_b</parent>
      </property>
      <property>
            <name>cl_usage_stats_tms_tree</name>
            <table>objects</table>
            <group>cl_usage_stats_tms</group>
            <field>meta</field>
            <method>serialize</method>
            <type>treeview</type>
            <no_caption>1</no_caption>
            <parent>cl_usage_stats_tms_tree</parent>
            <store>no</store>
      </property>
      <property>
            <name>cl_usage_stats_tms_list</name>
            <table>objects</table>
            <group>cl_usage_stats_tms</group>
            <field>meta</field>
            <method>serialize</method>
            <type>table</type>
            <no_caption>1</no_caption>
            <store>no</store>
            <parent>cl_usage_stats_tms_right_split</parent>
      </property>
      <property>
            <name>errors_tree</name>
            <table>objects</table>
            <group>errors</group>
            <field>meta</field>
            <method>serialize</method>
            <type>treeview</type>
            <no_caption>1</no_caption>
            <parent>errors_tree</parent>
            <store>no</store>
      </property>
      <property>
            <name>errors_list_grapx</name>
            <table>objects</table>
            <group>errors</group>
            <field>meta</field>
            <method>serialize</method>
            <type>google_chart</type>
            <no_caption>1</no_caption>
            <store>no</store>
            <parent>errors_right_split_gp_v</parent>
      </property>
      <property>
            <name>errors_list_grapx_days</name>
            <table>objects</table>
            <group>errors</group>
            <field>meta</field>
            <method>serialize</method>
            <type>google_chart</type>
            <no_caption>1</no_caption>
            <store>no</store>
            <parent>errors_right_split_gp_v</parent>
      </property>
      <property>
            <name>errors_list</name>
            <table>objects</table>
            <group>errors</group>
            <field>meta</field>
            <method>serialize</method>
            <type>table</type>
            <no_caption>1</no_caption>
            <store>no</store>
            <parent>errors_right_split</parent>
      </property>
      <property>
            <name>sites_sites_toolbar</name>
            <table>objects</table>
            <group>sites_sites</group>
            <field>meta</field>
            <method>serialize</method>
            <type>toolbar</type>
            <no_caption>1</no_caption>
            <store>no</store>
      </property>
      <property>
            <name>sites_sites_grp_tree</name>
            <table>objects</table>
            <group>sites_sites</group>
            <field>meta</field>
            <method>serialize</method>
            <type>treeview</type>
            <no_caption>1</no_caption>
            <parent>sites_sites_tree</parent>
            <store>no</store>
      </property>
      <property>
            <name>sites_list_grapx</name>
            <table>objects</table>
            <group>sites_sites</group>
            <field>meta</field>
            <method>serialize</method>
            <type>google_chart</type>
            <store>no</store>
            <no_caption>1</no_caption>
            <parent>sites_sites_right_split_t</parent>
      </property>
      <property>
            <name>sites_list</name>
            <table>objects</table>
            <group>sites_sites</group>
            <field>meta</field>
            <method>serialize</method>
            <type>table</type>
            <store>no</store>
            <no_caption>1</no_caption>
            <parent>sites_sites_right_split</parent>
      </property>
      <property>
            <name>sites_servers_grp_tree</name>
            <table>objects</table>
            <group>sites_servers</group>
            <field>meta</field>
            <method>serialize</method>
            <type>treeview</type>
            <no_caption>1</no_caption>
            <parent>sites_servers_tree</parent>
            <store>no</store>
      </property>
      <property>
            <name>sites_servers_grapx</name>
            <table>objects</table>
            <group>sites_servers</group>
            <field>meta</field>
            <method>serialize</method>
            <type>google_chart</type>
            <store>no</store>
            <no_caption>1</no_caption>
            <parent>sites_servers_right_split_g</parent>
      </property>
      <property>
            <name>sites_servers</name>
            <table>objects</table>
            <group>sites_servers</group>
            <field>meta</field>
            <method>serialize</method>
            <type>table</type>
            <store>no</store>
            <no_caption>1</no_caption>
            <parent>sites_servers_right_split</parent>
      </property>
      <property>
            <name>notif_tb</name>
            <table>objects</table>
            <group>notifications_rules</group>
            <field>meta</field>
            <method>serialize</method>
            <type>toolbar</type>
            <store>no</store>
            <no_caption>1</no_caption>
      </property>
      <property>
            <name>notifications_rules</name>
            <table>objects</table>
            <group>notifications_rules</group>
            <field>meta</field>
            <method>serialize</method>
            <type>table</type>
            <store>no</store>
            <no_caption>1</no_caption>
            <caption>Reeglid</caption>
      </property>
      <property>
            <name>notifications_sent_site_tree</name>
            <table>objects</table>
            <group>notifications_sent</group>
            <field>meta</field>
            <method>serialize</method>
            <type>treeview</type>
            <no_caption>1</no_caption>
            <parent>notifications_sent_tree</parent>
            <store>no</store>
      </property>
      <property>
            <name>notifications_sent_site_tree_rules</name>
            <table>objects</table>
            <group>notifications_sent</group>
            <field>meta</field>
            <method>serialize</method>
            <type>treeview</type>
            <no_caption>1</no_caption>
            <parent>notifications_sent_tree_rules</parent>
            <store>no</store>
      </property>
      <property>
            <name>notifications_sent_grapx</name>
            <table>objects</table>
            <group>notifications_sent</group>
            <field>meta</field>
            <method>serialize</method>
            <type>google_chart</type>
            <store>no</store>
            <no_caption>1</no_caption>
            <parent>notifications_sent_grapx</parent>
      </property>
      <property>
            <name>notifications_sent</name>
            <table>objects</table>
            <group>notifications_sent</group>
            <field>meta</field>
            <method>serialize</method>
            <type>table</type>
            <store>no</store>
            <no_caption>1</no_caption>
            <parent>notifications_sent_right_split</parent>
      </property>
      <property>
            <name>ns_next</name>
            <table>objects</table>
            <group>notifications_status</group>
            <field>meta</field>
            <method>serialize</method>
            <type>text</type>
            <store>no</store>
            <caption>J&amp;amp;auml;rgmine k&amp;amp;auml;ivitus</caption>
      </property>
      <property>
            <name>ns_manual</name>
            <table>objects</table>
            <group>notifications_status</group>
            <field>meta</field>
            <method>serialize</method>
            <type>text</type>
            <store>no</store>
            <caption>K&amp;amp;auml;ivita kohe</caption>
      </property>
      <classinfo>
            <relationmgr>yes</relationmgr>
            <no_comment>1</no_comment>
            <no_status>1</no_status>
            <prop_cb>1</prop_cb>
      </classinfo>
      <groupinfo>
            <classes>
                  <caption>Klassid</caption>
            </classes>
            <classes_classes>
                  <caption>Klassid</caption>
                  <parent>classes</parent>
            </classes_classes>
            <classes_props>
                  <caption>Omadused</caption>
                  <parent>classes</parent>
            </classes_props>
            <mgr>
                  <caption>Lisamise puu</caption>
                  <submit>no</submit>
                  <parent>classes</parent>
            </mgr>
            <rels>
                  <caption>Seosed</caption>
                  <submit>no</submit>
                  <parent>classes</parent>
            </rels>
            <cl_usage_stats>
                  <caption>Statistika</caption>
            </cl_usage_stats>
            <cl_usage_stats_clids>
                  <caption>Klasside TOP</caption>
                  <parent>cl_usage_stats</parent>
                  <submit>no</submit>
            </cl_usage_stats_clids>
            <cl_usage_stats_props>
                  <caption>Omadused</caption>
                  <parent>cl_usage_stats</parent>
                  <submit>no</submit>
            </cl_usage_stats_props>
            <cl_usage_stats_tms>
                  <caption>Ajad</caption>
                  <parent>cl_usage_stats</parent>
                  <submit>no</submit>
            </cl_usage_stats_tms>
            <errors>
                  <caption>Vead</caption>
            </errors>
            <sites>
                  <caption>Saidid</caption>
            </sites>
            <sites_sites>
                  <parent>sites</parent>
                  <caption>Saidid</caption>
            </sites_sites>
            <sites_servers>
                  <parent>sites</parent>
                  <caption>Serverid</caption>
                  <submit>no</submit>
            </sites_servers>
            <notifications>
                  <caption>Teavitus</caption>
            </notifications>
            <notifications_sent>
                  <caption>Saadetud teavitused</caption>
                  <parent>notifications</parent>
                  <save>no</save>
                  <submit>no</submit>
            </notifications_sent>
            <notifications_rules>
                  <caption>Reeglid</caption>
                  <parent>notifications</parent>
                  <submit>no</submit>
            </notifications_rules>
            <notifications_status>
                  <caption>Staatus</caption>
                  <parent>notifications</parent>
                  <save>no</save>
                  <submit>no</submit>
            </notifications_status>
      </groupinfo>
      <reltypes>
            <NOTIFICATION_RULE>
                  <value>1</value>
                  <clid>CL_SITE_NOTIFICATION_RULE</clid>
                  <caption>Teavituse reegel</caption>
            </NOTIFICATION_RULE>
      </reltypes>
      <layout>
            <mgr_hbox>
                  <type>hbox</type>
                  <width>20%:80%</width>
                  <group>mgr</group>
                  <area_caption></area_caption>
            </mgr_hbox>
            <mgr_tree_box>
                  <type>vbox</type>
                  <closeable>1</closeable>
                  <area_caption>Klasside&amp;amp;nbsp;kaustad</area_caption>
                  <parent>mgr_hbox</parent>
                  <group>mgr</group>
            </mgr_tree_box>
            <rels_hbox>
                  <type>hbox</type>
                  <width>20%:80%</width>
                  <group>rels</group>
                  <area_caption></area_caption>
            </rels_hbox>
            <rels_tree_box>
                  <type>vbox</type>
                  <closeable>1</closeable>
                  <area_caption>Klasside&amp;amp;nbsp;kaustad</area_caption>
                  <parent>rels_hbox</parent>
                  <group>rels</group>
            </rels_tree_box>
            <classes_split>
                  <type>hbox</type>
                  <group>classes_classes</group>
                  <area_caption></area_caption>
            </classes_split>
            <classes_left>
                  <type>vbox</type>
                  <parent>classes_split</parent>
                  <group>classes_classes</group>
                  <area_caption></area_caption>
            </classes_left>
            <classes_tree>
                  <type>vbox</type>
                  <area_caption>Klasside&amp;amp;nbsp;puu</area_caption>
                  <closeable>1</closeable>
                  <parent>classes_left</parent>
                  <group>classes_classes</group>
            </classes_tree>
            <classes_groups>
                  <type>vbox</type>
                  <area_caption>Klasside&amp;amp;nbsp;grupid</area_caption>
                  <closeable>1</closeable>
                  <parent>classes_left</parent>
                  <group>classes_classes</group>
            </classes_groups>
            <classes_props_split>
                  <type>hbox</type>
                  <group>classes_props</group>
                  <area_caption></area_caption>
            </classes_props_split>
            <classes_props_left>
                  <type>vbox</type>
                  <parent>classes_props_split</parent>
                  <group>classes_props</group>
                  <area_caption></area_caption>
            </classes_props_left>
            <classes_props_tree>
                  <type>vbox</type>
                  <area_caption>Klasside&amp;amp;nbsp;puu</area_caption>
                  <closeable>1</closeable>
                  <parent>classes_props_left</parent>
                  <group>classes_props</group>
            </classes_props_tree>
            <classes_props_groups>
                  <type>vbox</type>
                  <area_caption>Omaduste&amp;amp;nbsp;grupid</area_caption>
                  <closeable>1</closeable>
                  <parent>classes_props_left</parent>
                  <group>classes_props</group>
            </classes_props_groups>
            <cl_usage_stats_split>
                  <type>hbox</type>
                  <width>20%:80%</width>
                  <group>cl_usage_stats_clids</group>
                  <area_caption></area_caption>
            </cl_usage_stats_split>
            <cl_usage_stats_left>
                  <type>vbox</type>
                  <parent>cl_usage_stats_split</parent>
                  <group>cl_usage_stats_clids</group>
                  <area_caption></area_caption>
            </cl_usage_stats_left>
            <cl_usage_stats_tree>
                  <type>vbox</type>
                  <area_caption>Klasside&amp;amp;nbsp;puu</area_caption>
                  <closeable>1</closeable>
                  <parent>cl_usage_stats_left</parent>
                  <group>cl_usage_stats_clids</group>
            </cl_usage_stats_tree>
            <cl_usage_stats_groups>
                  <type>vbox</type>
                  <area_caption>Klasside&amp;amp;nbsp;grupid</area_caption>
                  <closeable>1</closeable>
                  <parent>cl_usage_stats_left</parent>
                  <group>cl_usage_stats_clids</group>
            </cl_usage_stats_groups>
            <cl_usage_stats_right>
                  <type>vbox</type>
                  <parent>cl_usage_stats_split</parent>
                  <group>cl_usage_stats_clids</group>
                  <area_caption></area_caption>
            </cl_usage_stats_right>
            <cl_usage_stats_right_split>
                  <type>hbox</type>
                  <parent>cl_usage_stats_right</parent>
                  <group>cl_usage_stats_clids</group>
                  <area_caption></area_caption>
            </cl_usage_stats_right_split>
            <cl_usage_stats_right_split_1>
                  <type>vbox</type>
                  <parent>cl_usage_stats_right_split</parent>
                  <group>cl_usage_stats_clids</group>
                  <area_caption></area_caption>
            </cl_usage_stats_right_split_1>
            <cl_usage_stats_right_split_1_v>
                  <type>vbox</type>
                  <parent>cl_usage_stats_right_split_1</parent>
                  <area_caption>Graafikud</area_caption>
                  <closeable>1</closeable>
                  <group>cl_usage_stats_clids</group>
            </cl_usage_stats_right_split_1_v>
            <cl_usage_stats_right_split_2>
                  <type>vbox</type>
                  <parent>cl_usage_stats_right_split</parent>
                  <group>cl_usage_stats_clids</group>
                  <area_caption></area_caption>
            </cl_usage_stats_right_split_2>
            <cl_usage_stats_right_split_2_v>
                  <type>vbox</type>
                  <parent>cl_usage_stats_right_split_2</parent>
                  <area_caption>Graafikud</area_caption>
                  <closeable>1</closeable>
                  <group>cl_usage_stats_clids</group>
            </cl_usage_stats_right_split_2_v>
            <cl_usage_props_stats_split>
                  <type>hbox</type>
                  <width>20%:80%</width>
                  <group>cl_usage_stats_props</group>
                  <area_caption></area_caption>
            </cl_usage_props_stats_split>
            <cl_usage_props_stats_left>
                  <type>vbox</type>
                  <parent>cl_usage_props_stats_split</parent>
                  <group>cl_usage_stats_props</group>
                  <area_caption></area_caption>
            </cl_usage_props_stats_left>
            <cl_usage_props_stats_tree>
                  <type>vbox</type>
                  <area_caption>Klasside&amp;amp;nbsp;puu</area_caption>
                  <closeable>1</closeable>
                  <parent>cl_usage_props_stats_left</parent>
                  <group>cl_usage_stats_props</group>
            </cl_usage_props_stats_tree>
            <cl_usage_props_stats_groups>
                  <type>vbox</type>
                  <area_caption>Klasside&amp;amp;nbsp;grupid</area_caption>
                  <closeable>1</closeable>
                  <parent>cl_usage_props_stats_left</parent>
                  <group>cl_usage_stats_props</group>
            </cl_usage_props_stats_groups>
            <cl_usage_props_stats_right>
                  <type>vbox</type>
                  <parent>cl_usage_props_stats_split</parent>
                  <group>cl_usage_stats_props</group>
                  <area_caption></area_caption>
            </cl_usage_props_stats_right>
            <cl_usage_props_stats_right_split>
                  <type>vbox</type>
                  <parent>cl_usage_props_stats_right</parent>
                  <group>cl_usage_stats_props</group>
                  <area_caption></area_caption>
            </cl_usage_props_stats_right_split>
            <cl_usage_props_stats_right_split_v>
                  <type>vbox</type>
                  <parent>cl_usage_props_stats_right</parent>
                  <area_caption>Graafikud</area_caption>
                  <closeable>1</closeable>
                  <group>cl_usage_stats_props</group>
            </cl_usage_props_stats_right_split_v>
            <cl_usage_props_stats_right_split_b>
                  <type>vbox</type>
                  <parent>cl_usage_props_stats_right</parent>
                  <group>cl_usage_stats_props</group>
                  <area_caption></area_caption>
            </cl_usage_props_stats_right_split_b>
            <cl_usage_stats_tms_split>
                  <type>hbox</type>
                  <width>20%:80%</width>
                  <group>cl_usage_stats_tms</group>
                  <area_caption></area_caption>
            </cl_usage_stats_tms_split>
            <cl_usage_stats_tms_left>
                  <type>vbox</type>
                  <parent>cl_usage_stats_tms_split</parent>
                  <group>cl_usage_stats_tms</group>
                  <area_caption></area_caption>
            </cl_usage_stats_tms_left>
            <cl_usage_stats_tms_tree>
                  <type>vbox</type>
                  <area_caption>Saidid</area_caption>
                  <closeable>1</closeable>
                  <parent>cl_usage_stats_tms_left</parent>
                  <group>cl_usage_stats_tms</group>
            </cl_usage_stats_tms_tree>
            <cl_usage_stats_tms_right>
                  <type>vbox</type>
                  <parent>cl_usage_stats_tms_split</parent>
                  <group>cl_usage_stats_tms</group>
                  <area_caption></area_caption>
            </cl_usage_stats_tms_right>
            <cl_usage_stats_tms_right_split>
                  <type>hbox</type>
                  <parent>cl_usage_stats_tms_right</parent>
                  <group>cl_usage_stats_tms</group>
                  <area_caption></area_caption>
            </cl_usage_stats_tms_right_split>
            <errors_split>
                  <type>hbox</type>
                  <width>20%:80%</width>
                  <group>errors</group>
                  <area_caption></area_caption>
            </errors_split>
            <errors_left>
                  <type>vbox</type>
                  <parent>errors_split</parent>
                  <group>errors</group>
                  <area_caption></area_caption>
            </errors_left>
            <errors_tree>
                  <type>vbox</type>
                  <area_caption>Saidid</area_caption>
                  <closeable>1</closeable>
                  <parent>errors_left</parent>
                  <group>errors</group>
            </errors_tree>
            <errors_right>
                  <type>vbox</type>
                  <parent>errors_split</parent>
                  <group>errors</group>
                  <area_caption></area_caption>
            </errors_right>
            <errors_right_split>
                  <type>vbox</type>
                  <parent>errors_right</parent>
                  <group>errors</group>
                  <area_caption></area_caption>
            </errors_right_split>
            <errors_right_split_gp>
                  <type>vbox</type>
                  <parent>errors_right_split</parent>
                  <closeable>1</closeable>
                  <area_caption>Graafikud</area_caption>
                  <group>errors</group>
            </errors_right_split_gp>
            <errors_right_split_gp_v>
                  <type>hbox</type>
                  <parent>errors_right_split_gp</parent>
                  <group>errors</group>
                  <area_caption></area_caption>
            </errors_right_split_gp_v>
            <sites_sites_split>
                  <type>hbox</type>
                  <width>20%:80%</width>
                  <group>sites_sites</group>
                  <area_caption></area_caption>
            </sites_sites_split>
            <sites_sites_left>
                  <type>vbox</type>
                  <parent>sites_sites_split</parent>
                  <group>sites_sites</group>
                  <area_caption></area_caption>
            </sites_sites_left>
            <sites_sites_tree>
                  <type>vbox</type>
                  <area_caption>Grupid</area_caption>
                  <closeable>1</closeable>
                  <parent>sites_sites_left</parent>
                  <group>sites_sites</group>
            </sites_sites_tree>
            <sites_sites_right>
                  <type>vbox</type>
                  <parent>sites_sites_split</parent>
                  <group>sites_sites</group>
                  <area_caption></area_caption>
            </sites_sites_right>
            <sites_sites_right_split>
                  <type>vbox</type>
                  <parent>sites_sites_right</parent>
                  <group>sites_sites</group>
                  <area_caption></area_caption>
            </sites_sites_right_split>
            <sites_sites_right_split_t>
                  <type>vbox</type>
                  <parent>sites_sites_right_split</parent>
                  <closeable>1</closeable>
                  <area_caption>Graafikud</area_caption>
                  <group>sites_sites</group>
            </sites_sites_right_split_t>
            <sites_servers_split>
                  <type>hbox</type>
                  <width>20%:80%</width>
                  <group>sites_servers</group>
                  <area_caption></area_caption>
            </sites_servers_split>
            <sites_servers_left>
                  <type>vbox</type>
                  <parent>sites_servers_split</parent>
                  <group>sites_servers</group>
                  <area_caption></area_caption>
            </sites_servers_left>
            <sites_servers_tree>
                  <type>vbox</type>
                  <area_caption>Filter</area_caption>
                  <closeable>1</closeable>
                  <parent>sites_servers_left</parent>
                  <group>sites_servers</group>
            </sites_servers_tree>
            <sites_servers_right>
                  <type>vbox</type>
                  <parent>sites_servers_split</parent>
                  <group>sites_servers</group>
                  <area_caption></area_caption>
            </sites_servers_right>
            <sites_servers_right_split>
                  <type>vbox</type>
                  <parent>sites_servers_right</parent>
                  <group>sites_servers</group>
                  <area_caption></area_caption>
            </sites_servers_right_split>
            <sites_servers_right_split_g>
                  <type>vbox</type>
                  <parent>sites_servers_right_split</parent>
                  <area_caption>Graafikud</area_caption>
                  <group>sites_servers</group>
            </sites_servers_right_split_g>
            <notifications_sent_split>
                  <type>hbox</type>
                  <width>20%:80%</width>
                  <group>notifications_sent</group>
                  <area_caption></area_caption>
            </notifications_sent_split>
            <notifications_sent_left>
                  <type>vbox</type>
                  <parent>notifications_sent_split</parent>
                  <group>notifications_sent</group>
                  <area_caption></area_caption>
            </notifications_sent_left>
            <notifications_sent_tree>
                  <type>vbox</type>
                  <area_caption>Saitide&amp;amp;nbsp;grupid</area_caption>
                  <closeable>1</closeable>
                  <parent>notifications_sent_left</parent>
                  <group>notifications_sent</group>
            </notifications_sent_tree>
            <notifications_sent_tree_rules>
                  <type>vbox</type>
                  <area_caption>Teavituse&amp;amp;nbsp;reeglid</area_caption>
                  <closeable>1</closeable>
                  <parent>notifications_sent_left</parent>
                  <group>notifications_sent</group>
            </notifications_sent_tree_rules>
            <notifications_sent_right>
                  <type>vbox</type>
                  <parent>notifications_sent_split</parent>
                  <group>notifications_sent</group>
                  <area_caption></area_caption>
            </notifications_sent_right>
            <notifications_sent_right_split>
                  <type>vbox</type>
                  <parent>notifications_sent_right</parent>
                  <group>notifications_sent</group>
                  <area_caption></area_caption>
            </notifications_sent_right_split>
            <notifications_sent_grapx>
                  <type>vbox</type>
                  <area_caption>Teavituste&amp;amp;nbsp;TOP&amp;amp;nbsp;10</area_caption>
                  <closeable>1</closeable>
                  <parent>notifications_sent_right_split</parent>
                  <group>notifications_sent</group>
            </notifications_sent_grapx>
      </layout>
</properties>

